dataclasses_serialization/__init__.py
dataclasses_serialization/bson.py
dataclasses_serialization/json.py
dataclasses_serialization/serializer_base/__init__.py
dataclasses_serialization/serializer_base/dataclasses.py
dataclasses_serialization/serializer_base/dictionary.py
dataclasses_serialization/serializer_base/errors.py
dataclasses_serialization/serializer_base/list.py
dataclasses_serialization/serializer_base/noop.py
dataclasses_serialization/serializer_base/refinement_dict.py
dataclasses_serialization/serializer_base/serializer.py
dataclasses_serialization/serializer_base/typing.py
dataclasses_serialization/serializer_base/union.py
dataclasses_serialization-1.3.0.dist-info/LICENSE
dataclasses_serialization-1.3.0.dist-info/METADATA
dataclasses_serialization-1.3.0.dist-info/WHEEL
dataclasses_serialization-1.3.0.dist-info/top_level.txt
dataclasses_serialization-1.3.0.dist-info/RECORD
