Metadata-Version: 2.1
Name: dataclasses-serialization
Version: 1.3.0
Summary: Serialize/deserialize Python dataclasses to various other data formats
Home-page: https://github.com/madman-bob/python-dataclasses-serialization
Author: Robert Wright
Author-email: madman.bob@hotmail.co.uk
License: MIT
Platform: UNKNOWN
Classifier: License :: OSI Approved :: MIT License
Classifier: Programming Language :: Python :: 3
Classifier: Programming Language :: Python :: 3.6
Classifier: Programming Language :: Python :: 3.7
Classifier: Programming Language :: Python :: 3.8
Requires-Python: >=3.6
Requires-Dist: dataclasses
Requires-Dist: more-properties (>=1.1.0)
Requires-Dist: typing-inspect
Requires-Dist: toolz
Requires-Dist: toposort
Requires-Dist: twine
